{
  "images": [
    {
      "file_name": "ezgif-frame-001.jpg",
      "height": 1080,
      "width": 1920,
      "id": 1
    },
    {
      "file_name": "ezgif-frame-002.jpg",
      "height": 1080,
      "width": 1920,
      "id": 2
    },
    {
      "file_name": "ezgif-frame-003.jpg",
      "height": 1080,
      "width": 1920,
      "id": 3
    },
    {
      "file_name": "ezgif-frame-004.jpg",
      "height": 1080,
      "width": 1920,
      "id": 4
    },
    {
      "file_name": "ezgif-frame-005.jpg",
      "height": 1080,
      "width": 1920,
      "id": 5
    },
    {
      "file_name": "ezgif-frame-006.jpg",
      "height": 1080,
      "width": 1920,
      "id": 6
    },
    {
      "file_name": "ezgif-frame-007.jpg",
      "height": 1080,
      "width": 1920,
      "id": 7
    },
    {
      "file_name": "ezgif-frame-008.jpg",
      "height": 1080,
      "width": 1920,
      "id": 8
    },
    {
      "file_name": "ezgif-frame-009.jpg",
      "height": 1080,
      "width": 1920,
      "id": 9
    },
    {
      "file_name": "ezgif-frame-011.jpg",
      "height": 1080,
      "width": 1920,
      "id": 10
    },
    {
      "file_name": "ezgif-frame-014.jpg",
      "height": 1080,
      "width": 1920,
      "id": 11
    },
    {
      "file_name": "ezgif-frame-015.jpg",
      "height": 1080,
      "width": 1920,
      "id": 12
    },
    {
      "file_name": "ezgif-frame-016.jpg",
      "height": 1080,
      "width": 1920,
      "id": 13
    },
    {
      "file_name": "ezgif-frame-017.jpg",
      "height": 1080,
      "width": 1920,
      "id": 14
    },
    {
      "file_name": "ezgif-frame-018.jpg",
      "height": 1080,
      "width": 1920,
      "id": 15
    },
    {
      "file_name": "ezgif-frame-019.jpg",
      "height": 1080,
      "width": 1920,
      "id": 16
    },
    {
      "file_name": "ezgif-frame-020.jpg",
      "height": 1080,
      "width": 1920,
      "id": 17
    },
    {
      "file_name": "ezgif-frame-021.jpg",
      "height": 1080,
      "width": 1920,
      "id": 18
    },
    {
      "file_name": "ezgif-frame-022.jpg",
      "height": 1080,
      "width": 1920,
      "id": 19
    },
    {
      "file_name": "ezgif-frame-023.jpg",
      "height": 1080,
      "width": 1920,
      "id": 20
    },
    {
      "file_name": "ezgif-frame-024.jpg",
      "height": 1080,
      "width": 1920,
      "id": 21
    },
    {
      "file_name": "ezgif-frame-026.jpg",
      "height": 1080,
      "width": 1920,
      "id": 22
    },
    {
      "file_name": "ezgif-frame-035.jpg",
      "height": 1080,
      "width": 1920,
      "id": 23
    },
    {
      "file_name": "ezgif-frame-036.jpg",
      "height": 1080,
      "width": 1920,
      "id": 24
    },
    {
      "file_name": "ezgif-frame-037.jpg",
      "height": 1080,
      "width": 1920,
      "id": 25
    },
    {
      "file_name": "ezgif-frame-039.jpg",
      "height": 1080,
      "width": 1920,
      "id": 26
    },
    {
      "file_name": "ezgif-frame-041.jpg",
      "height": 1080,
      "width": 1920,
      "id": 27
    },
    {
      "file_name": "ezgif-frame-042.jpg",
      "height": 1080,
      "width": 1920,
      "id": 28
    },
    {
      "file_name": "ezgif-frame-013.jpg",
      "height": 1080,
      "width": 1920,
      "id": 29
    },
    {
      "file_name": "ezgif-frame-033.jpg",
      "height": 1080,
      "width": 1920,
      "id": 30
    },
    {
      "file_name": "ezgif-frame-043.jpg",
      "height": 1080,
      "width": 1920,
      "id": 31
    },
    {
      "file_name": "ezgif-frame-045.jpg",
      "height": 1080,
      "width": 1920,
      "id": 32
    },
    {
      "file_name": "ezgif-frame-046.jpg",
      "height": 1080,
      "width": 1920,
      "id": 33
    },
    {
      "file_name": "ezgif-frame-052.jpg",
      "height": 1080,
      "width": 1920,
      "id": 34
    },
    {
      "file_name": "ezgif-frame-053.jpg",
      "height": 1080,
      "width": 1920,
      "id": 35
    },
    {
      "file_name": "ezgif-frae-004.jpg",
      "height": 1080,
      "width": 1920,
      "id": 36
    },
    {
      "file_name": "ezgif-frae-023.jpg",
      "height": 1080,
      "width": 1920,
      "id": 37
    },
    {
      "file_name": "ezgif-frae-024.jpg",
      "height": 1080,
      "width": 1920,
      "id": 38
    },
    {
      "file_name": "ezgif-frae-025.jpg",
      "height": 1080,
      "width": 1920,
      "id": 39
    },
    {
      "file_name": "ezgif-frae-033.jpg",
      "height": 1080,
      "width": 1920,
      "id": 40
    },
    {
      "file_name": "ezgif-frae-036.jpg",
      "height": 1080,
      "width": 1920,
      "id": 41
    },
    {
      "file_name": "ezgif-frae-041.jpg",
      "height": 1080,
      "width": 1920,
      "id": 42
    },
    {
      "file_name": "ezgif-frae-042.jpg",
      "height": 1080,
      "width": 1920,
      "id": 43
    },
    {
      "file_name": "ezgif-frae-043.jpg",
      "height": 1080,
      "width": 1920,
      "id": 44
    },
    {
      "file_name": "ezgif-frae-045.jpg",
      "height": 1080,
      "width": 1920,
      "id": 45
    },
    {
      "file_name": "ezgif-frae-046.jpg",
      "height": 1080,
      "width": 1920,
      "id": 46
    },
    {
      "file_name": "ezgif-frae-052.jpg",
      "height": 1080,
      "width": 1920,
      "id": 47
    },
    {
      "file_name": "ezgif-frae-053.jpg",
      "height": 1080,
      "width": 1920,
      "id": 48
    },
    {
      "file_name": "ezgif-fre-021.jpg",
      "height": 1080,
      "width": 1920,
      "id": 49
    },
    {
      "file_name": "ezgif-fme-002.jpg",
      "height": 1080,
      "width": 1920,
      "id": 50
    },
    {
      "file_name": "ezgif-fre-001.jpg",
      "height": 1080,
      "width": 1920,
      "id": 51
    },
    {
      "file_name": "ezgif-fre-003.jpg",
      "height": 1080,
      "width": 1920,
      "id": 52
    },
    {
      "file_name": "ezgif-fre-004.jpg",
      "height": 1080,
      "width": 1920,
      "id": 53
    },
    {
      "file_name": "ezgif-fre-005.jpg",
      "height": 1080,
      "width": 1920,
      "id": 54
    },
    {
      "file_name": "ezgif-fre-007.jpg",
      "height": 1080,
      "width": 1920,
      "id": 55
    },
    {
      "file_name": "ezgif-fre-008.jpg",
      "height": 1080,
      "width": 1920,
      "id": 56
    },
    {
      "file_name": "ezgif-fre-009.jpg",
      "height": 1080,
      "width": 1920,
      "id": 57
    },
    {
      "file_name": "ezgif-fre-011.jpg",
      "height": 1080,
      "width": 1920,
      "id": 58
    },
    {
      "file_name": "ezgif-fre-012.jpg",
      "height": 1080,
      "width": 1920,
      "id": 59
    },
    {
      "file_name": "ezgif-fre-014.jpg",
      "height": 1080,
      "width": 1920,
      "id": 60
    },
    {
      "file_name": "ezgif-fre-015.jpg",
      "height": 1080,
      "width": 1920,
      "id": 61
    },
    {
      "file_name": "ezgif-fre-016.jpg",
      "height": 1080,
      "width": 1920,
      "id": 62
    },
    {
      "file_name": "ezgif-fre-017.jpg",
      "height": 1080,
      "width": 1920,
      "id": 63
    },
    {
      "file_name": "ezgif-fre-018.jpg",
      "height": 1080,
      "width": 1920,
      "id": 64
    },
    {
      "file_name": "ezgif-fre-019.jpg",
      "height": 1080,
      "width": 1920,
      "id": 65
    },
    {
      "file_name": "ezgif-fre-023.jpg",
      "height": 1080,
      "width": 1920,
      "id": 66
    },
    {
      "file_name": "ezgif-fre-024.jpg",
      "height": 1080,
      "width": 1920,
      "id": 67
    },
    {
      "file_name": "ezgif-fre-026.jpg",
      "height": 1080,
      "width": 1920,
      "id": 68
    },
    {
      "file_name": "ezgif-fre-035.jpg",
      "height": 1080,
      "width": 1920,
      "id": 69
    },
    {
      "file_name": "ezgif-fre-036.jpg",
      "height": 1080,
      "width": 1920,
      "id": 70
    },
    {
      "file_name": "ezgif-fre-037.jpg",
      "height": 1080,
      "width": 1920,
      "id": 71
    },
    {
      "file_name": "ezgif-fre-039.jpg",
      "height": 1080,
      "width": 1920,
      "id": 72
    },
    {
      "file_name": "ezgif-fre-041.jpg",
      "height": 1080,
      "width": 1920,
      "id": 73
    },
    {
      "file_name": "ezgif-fre-042.jpg",
      "height": 1080,
      "width": 1920,
      "id": 74
    }
  ],
  "categories": [
    {
      "id": 1,
      "name": "BalanceUNI7"
    },
    {
      "id": 2,
      "name": "TabletteUNI7"
    },
    {
      "id": 3,
      "name": "PowerSwitch"
    }
  ],
  "annotations": [
    {
      "id": 1,
      "image_id": 1,
      "category_id": 1,
      "area": 659497.0,
      "iscrowd": 0,
      "segmentation": [
        [
          655,
          262,
          253,
          676,
          353,
          909,
          1053,
          1011,
          1155,
          748,
          1548,
          697,
          1565,
          665,
          1518,
          323,
          1493,
          318,
          1176,
          393,
          1174,
          339,
          1153,
          339,
          1148,
          286,
          653,
          262
        ]
      ],
      "bbox": [
        253,
        262,
        1312,
        749
      ]
    },
    {
      "id": 2,
      "image_id": 1,
      "category_id": 2,
      "area": 166874.5,
      "iscrowd": 0,
      "segmentation": [
        [
          1116,
          411,
          1490,
          318,
          1518,
          323,
          1562,
          669,
          1539,
          702,
          1025,
          746,
          1123,
          413
        ]
      ],
      "bbox": [
        1025,
        318,
        537,
        428
      ]
    },
    {
      "id": 3,
      "image_id": 2,
      "category_id": 1,
      "area": 755386.0,
      "iscrowd": 0,
      "segmentation": [
        [
          512,
          -10,
          333,
          133,
          246,
          233,
          133,
          423,
          187,
          705,
          923,
          787,
          1000,
          612,
          1376,
          812,
          1407,
          779,
          1376,
          353,
          1051,
          151,
          1048,
          84,
          1020,
          30,
          656,
          -2,
          507,
          0
        ]
      ],
      "bbox": [
        133,
        -10,
        1274,
        822
      ]
    },
    {
      "id": 4,
      "image_id": 2,
      "category_id": 2,
      "area": 177668.0,
      "iscrowd": 0,
      "segmentation": [
        [
          1046,
          158,
          946,
          528,
          1376,
          812,
          1402,
          776,
          1371,
          341,
          1046,
          148
        ]
      ],
      "bbox": [
        946,
        148,
        456,
        664
      ]
    },
    {
      "id": 5,
      "image_id": 3,
      "category_id": 1,
      "area": 643001.5,
      "iscrowd": 0,
      "segmentation": [
        [
          1130,
          174,
          641,
          146,
          465,
          276,
          332,
          506,
          309,
          569,
          365,
          820,
          1016,
          888,
          1032,
          865,
          1120,
          625,
          1513,
          574,
          1544,
          553,
          1500,
          216,
          1476,
          209,
          1155,
          276,
          1165,
          209,
          1132,
          216,
          1134,
          179
        ]
      ],
      "bbox": [
        309,
        146,
        1235,
        742
      ]
    },
    {
      "id": 6,
      "image_id": 3,
      "category_id": 2,
      "area": 161526.5,
      "iscrowd": 0,
      "segmentation": [
        [
          1106,
          295,
          1481,
          209,
          1504,
          211,
          1541,
          555,
          1506,
          569,
          1006,
          630,
          1097,
          288
        ]
      ],
      "bbox": [
        1006,
        209,
        535,
        421
      ]
    },
    {
      "id": 7,
      "image_id": 4,
      "category_id": 1,
      "area": 640224.0,
      "iscrowd": 0,
      "segmentation": [
        [
          1114,
          280,
          666,
          230,
          461,
          335,
          359,
          459,
          259,
          616,
          295,
          861,
          940,
          992,
          1050,
          742,
          1457,
          711,
          1473,
          678,
          1497,
          352,
          1452,
          323,
          1147,
          371,
          1147,
          330,
          1104,
          321,
          1111,
          278
        ]
      ],
      "bbox": [
        259,
        230,
        1238,
        762
      ]
    },
    {
      "id": 8,
      "image_id": 4,
      "category_id": 2,
      "area": 169040.0,
      "iscrowd": 0,
      "segmentation": [
        [
          1100,
          383,
          1454,
          326,
          1490,
          342,
          1471,
          688,
          1454,
          716,
          928,
          730,
          1100,
          380
        ]
      ],
      "bbox": [
        928,
        326,
        562,
        404
      ]
    },
    {
      "id": 9,
      "image_id": 5,
      "category_id": 1,
      "area": 634890.5,
      "iscrowd": 0,
      "segmentation": [
        [
          1228,
          251,
          774,
          177,
          565,
          282,
          422,
          397,
          331,
          557,
          414,
          820,
          971,
          957,
          1134,
          717,
          1474,
          717,
          1605,
          345,
          1280,
          365,
          1277,
          305,
          1242,
          260
        ]
      ],
      "bbox": [
        331,
        177,
        1274,
        780
      ]
    },
    {
      "id": 10,
      "image_id": 5,
      "category_id": 2,
      "area": 150899.0,
      "iscrowd": 0,
      "segmentation": [
        [
          982,
          668,
          1225,
          368,
          1608,
          342,
          1474,
          700,
          982,
          694
        ]
      ],
      "bbox": [
        982,
        342,
        626,
        358
      ]
    },
    {
      "id": 11,
      "image_id": 6,
      "category_id": 1,
      "area": 1108995.5,
      "iscrowd": 0,
      "segmentation": [
        [
          1121,
          256,
          1129,
          45,
          1078,
          -8,
          0,
          5,
          -2,
          751,
          167,
          878,
          256,
          840,
          445,
          1070,
          737,
          1086,
          1318,
          583,
          1108,
          272
        ]
      ],
      "bbox": [
        -2,
        -8,
        1320,
        1094
      ]
    },
    {
      "id": 12,
      "image_id": 6,
      "category_id": 2,
      "area": 641270.5,
      "iscrowd": 0,
      "segmentation": [
        [
          118,
          570,
          978,
          135,
          1321,
          575,
          724,
          1083,
          429,
          1064,
          121,
          578
        ]
      ],
      "bbox": [
        118,
        135,
        1203,
        948
      ]
    },
    {
      "id": 13,
      "image_id": 7,
      "category_id": 1,
      "area": 846914.0,
      "iscrowd": 0,
      "segmentation": [
        [
          1417,
          40,
          1314,
          2,
          668,
          2,
          308,
          242,
          368,
          634,
          937,
          840,
          1177,
          591,
          1511,
          648,
          1811,
          200,
          1777,
          154,
          1460,
          148,
          1454,
          88,
          1408,
          40
        ]
      ],
      "bbox": [
        308,
        2,
        1503,
        838
      ]
    },
    {
      "id": 14,
      "image_id": 7,
      "category_id": 2,
      "area": 246481.5,
      "iscrowd": 0,
      "segmentation": [
        [
          925,
          514,
          1340,
          160,
          1785,
          157,
          1805,
          205,
          1497,
          640,
          920,
          514
        ]
      ],
      "bbox": [
        920,
        157,
        885,
        483
      ]
    },
    {
      "id": 15,
      "image_id": 8,
      "category_id": 1,
      "area": 997411.5,
      "iscrowd": 0,
      "segmentation": [
        [
          427,
          2,
          70,
          272,
          5,
          356,
          -2,
          618,
          51,
          729,
          786,
          897,
          829,
          881,
          897,
          710,
          1324,
          986,
          1348,
          956,
          1443,
          421,
          1105,
          191,
          1108,
          86,
          1072,
          32,
          962,
          -2,
          421,
          0
        ]
      ],
      "bbox": [
        -2,
        -2,
        1445,
        988
      ]
    },
    {
      "id": 16,
      "image_id": 8,
      "category_id": 2,
      "area": 281066.0,
      "iscrowd": 0,
      "segmentation": [
        [
          854,
          624,
          1081,
          170,
          1454,
          427,
          1345,
          970,
          1321,
          991,
          843,
          640
        ]
      ],
      "bbox": [
        843,
        170,
        611,
        821
      ]
    },
    {
      "id": 17,
      "image_id": 9,
      "category_id": 1,
      "area": 1095082.5,
      "iscrowd": 0,
      "segmentation": [
        [
          1456,
          37,
          1332,
          5,
          570,
          -2,
          124,
          243,
          148,
          632,
          694,
          935,
          732,
          943,
          967,
          770,
          1216,
          864,
          1829,
          294,
          1805,
          243,
          1502,
          213,
          1486,
          132,
          1454,
          45
        ]
      ],
      "bbox": [
        124,
        -2,
        1705,
        945
      ]
    },
    {
      "id": 18,
      "image_id": 9,
      "category_id": 2,
      "area": 381709.5,
      "iscrowd": 0,
      "segmentation": [
        [
          683,
          600,
          1335,
          194,
          1810,
          248,
          1832,
          294,
          1216,
          851,
          670,
          640,
          689,
          605
        ]
      ],
      "bbox": [
        670,
        194,
        1162,
        657
      ]
    },
    {
      "id": 19,
      "image_id": 10,
      "category_id": 1,
      "area": 1073902.5,
      "iscrowd": 0,
      "segmentation": [
        [
          1597,
          127,
          1330,
          8,
          886,
          2,
          277,
          247,
          283,
          550,
          452,
          805,
          694,
          983,
          852,
          902,
          1005,
          980,
          1911,
          447,
          1897,
          386,
          1655,
          341,
          1672,
          230,
          1600,
          138
        ]
      ],
      "bbox": [
        277,
        2,
        1634,
        981
      ]
    },
    {
      "id": 20,
      "image_id": 10,
      "category_id": 2,
      "area": 425842.5,
      "iscrowd": 0,
      "segmentation": [
        [
          602,
          650,
          1430,
          294,
          1891,
          388,
          1916,
          452,
          994,
          977,
          591,
          675
        ]
      ],
      "bbox": [
        591,
        294,
        1325,
        683
      ]
    },
    {
      "id": 21,
      "image_id": 11,
      "category_id": 1,
      "area": 1233551.0,
      "iscrowd": 0,
      "segmentation": [
        [
          1382,
          554,
          1408,
          380,
          1345,
          291,
          817,
          74,
          0,
          417,
          5,
          1074,
          1214,
          1082,
          1671,
          697,
          1651,
          634,
          1385,
          562
        ]
      ],
      "bbox": [
        0,
        74,
        1671,
        1008
      ]
    },
    {
      "id": 22,
      "image_id": 11,
      "category_id": 2,
      "area": 477230.5,
      "iscrowd": 0,
      "segmentation": [
        [
          1148,
          511,
          205,
          1005,
          251,
          1068,
          1214,
          1080,
          1682,
          688,
          1645,
          622,
          1160,
          505
        ]
      ],
      "bbox": [
        205,
        505,
        1477,
        575
      ]
    },
    {
      "id": 23,
      "image_id": 12,
      "category_id": 1,
      "area": 1075753.5,
      "iscrowd": 0,
      "segmentation": [
        [
          1170,
          190,
          690,
          38,
          338,
          164,
          -3,
          383,
          6,
          748,
          680,
          1077,
          793,
          941,
          938,
          1077,
          1264,
          1083,
          1464,
          683,
          1193,
          396,
          1206,
          264,
          1177,
          190
        ]
      ],
      "bbox": [
        -3,
        38,
        1467,
        1045
      ]
    },
    {
      "id": 24,
      "image_id": 12,
      "category_id": 2,
      "area": 325902.0,
      "iscrowd": 0,
      "segmentation": [
        [
          716,
          812,
          1154,
          351,
          1467,
          683,
          1261,
          1080,
          938,
          1080,
          712,
          825
        ]
      ],
      "bbox": [
        712,
        351,
        755,
        729
      ]
    },
    {
      "id": 25,
      "image_id": 13,
      "category_id": 1,
      "area": 1530634.0,
      "iscrowd": 0,
      "segmentation": [
        [
          1446,
          481,
          1465,
          237,
          1375,
          143,
          1109,
          12,
          506,
          6,
          6,
          259,
          6,
          1071,
          1340,
          1081,
          1768,
          700,
          1750,
          634,
          1440,
          490
        ]
      ],
      "bbox": [
        6,
        6,
        1762,
        1075
      ]
    },
    {
      "id": 26,
      "image_id": 13,
      "category_id": 2,
      "area": 648015.5,
      "iscrowd": 0,
      "segmentation": [
        [
          203,
          962,
          1187,
          381,
          1750,
          631,
          1775,
          700,
          1346,
          1078,
          253,
          1078,
          209,
          962
        ]
      ],
      "bbox": [
        203,
        381,
        1572,
        697
      ]
    },
    {
      "id": 27,
      "image_id": 14,
      "category_id": 1,
      "area": 1595263.5,
      "iscrowd": 0,
      "segmentation": [
        [
          1406,
          454,
          1439,
          172,
          1369,
          51,
          1281,
          3,
          3,
          3,
          0,
          1066,
          1375,
          1081,
          1706,
          796,
          1693,
          745,
          1375,
          451
        ]
      ],
      "bbox": [
        0,
        3,
        1706,
        1078
      ]
    },
    {
      "id": 28,
      "image_id": 14,
      "category_id": 2,
      "area": 712797.5,
      "iscrowd": 0,
      "segmentation": [
        [
          124,
          945,
          1203,
          306,
          1703,
          748,
          1715,
          806,
          1366,
          1078,
          178,
          1072,
          118,
          939
        ]
      ],
      "bbox": [
        118,
        306,
        1597,
        772
      ]
    },
    {
      "id": 29,
      "image_id": 15,
      "category_id": 1,
      "area": 1583346.0,
      "iscrowd": 0,
      "segmentation": [
        [
          1425,
          440,
          1488,
          91,
          1391,
          2,
          0,
          8,
          0,
          794,
          202,
          1077,
          1374,
          1082,
          1671,
          817,
          1408,
          442
        ]
      ],
      "bbox": [
        0,
        2,
        1671,
        1080
      ]
    },
    {
      "id": 30,
      "image_id": 15,
      "category_id": 2,
      "area": 730312.0,
      "iscrowd": 0,
      "segmentation": [
        [
          122,
          942,
          1237,
          251,
          1671,
          808,
          1371,
          1077,
          200,
          1080,
          111,
          940
        ]
      ],
      "bbox": [
        111,
        251,
        1560,
        829
      ]
    },
    {
      "id": 31,
      "image_id": 16,
      "category_id": 1,
      "area": 1268269.5,
      "iscrowd": 0,
      "segmentation": [
        [
          1414,
          380,
          1440,
          57,
          1357,
          0,
          2,
          414,
          11,
          783,
          259,
          1085,
          1292,
          1080,
          1654,
          769,
          1390,
          395,
          1404,
          376
        ]
      ],
      "bbox": [
        2,
        0,
        1652,
        1085
      ]
    },
    {
      "id": 32,
      "image_id": 16,
      "category_id": 2,
      "area": 807135.0,
      "iscrowd": 0,
      "segmentation": [
        [
          88,
          857,
          1214,
          202,
          1652,
          759,
          1297,
          1073,
          264,
          1088,
          69,
          847
        ]
      ],
      "bbox": [
        69,
        202,
        1583,
        886
      ]
    },
    {
      "id": 33,
      "image_id": 17,
      "category_id": 1,
      "area": 1022197.5,
      "iscrowd": 0,
      "segmentation": [
        [
          1339,
          57,
          1200,
          -5,
          336,
          0,
          89,
          136,
          65,
          171,
          100,
          447,
          652,
          863,
          763,
          755,
          1000,
          1076,
          1084,
          1076,
          1521,
          597,
          1294,
          281,
          1336,
          134,
          1331,
          63
        ]
      ],
      "bbox": [
        65,
        -5,
        1456,
        1081
      ]
    },
    {
      "id": 34,
      "image_id": 17,
      "category_id": 2,
      "area": 367023.0,
      "iscrowd": 0,
      "segmentation": [
        [
          713,
          597,
          1242,
          231,
          1518,
          594,
          1078,
          1076,
          992,
          1073,
          689,
          607
        ]
      ],
      "bbox": [
        689,
        231,
        829,
        845
      ]
    },
    {
      "id": 35,
      "image_id": 18,
      "category_id": 1,
      "area": 1252324.0,
      "iscrowd": 0,
      "segmentation": [
        [
          1546,
          12,
          0,
          137,
          375,
          825,
          484,
          603,
          750,
          1068,
          1065,
          1084,
          1803,
          643,
          1618,
          321,
          1650,
          246,
          1578,
          0
        ]
      ],
      "bbox": [
        0,
        0,
        1803,
        1084
      ]
    },
    {
      "id": 36,
      "image_id": 18,
      "category_id": 2,
      "area": 768138.0,
      "iscrowd": 0,
      "segmentation": [
        [
          471,
          478,
          1446,
          118,
          1796,
          637,
          1068,
          1078,
          725,
          1056,
          459,
          496
        ]
      ],
      "bbox": [
        459,
        118,
        1337,
        960
      ]
    },
    {
      "id": 37,
      "image_id": 19,
      "category_id": 1,
      "area": 1108608.0,
      "iscrowd": 0,
      "segmentation": [
        [
          1717,
          308,
          1735,
          141,
          1685,
          -2,
          152,
          -2,
          485,
          661,
          561,
          444,
          838,
          1032,
          1838,
          573,
          1717,
          314
        ]
      ],
      "bbox": [
        152,
        -2,
        1686,
        1034
      ]
    },
    {
      "id": 38,
      "image_id": 19,
      "category_id": 2,
      "area": 724443.5,
      "iscrowd": 0,
      "segmentation": [
        [
          561,
          320,
          1552,
          44,
          1838,
          573,
          841,
          1029,
          550,
          332
        ]
      ],
      "bbox": [
        550,
        44,
        1288,
        985
      ]
    },
    {
      "id": 39,
      "image_id": 20,
      "category_id": 1,
      "area": 1155584.0,
      "iscrowd": 0,
      "segmentation": [
        [
          1812,
          350,
          1796,
          6,
          212,
          -3,
          475,
          553,
          771,
          1000,
          1875,
          612,
          1812,
          378
        ]
      ],
      "bbox": [
        212,
        -3,
        1663,
        1003
      ]
    },
    {
      "id": 40,
      "image_id": 20,
      "category_id": 2,
      "area": 860612.0,
      "iscrowd": 0,
      "segmentation": [
        [
          493,
          246,
          1428,
          3,
          1600,
          6,
          1871,
          603,
          771,
          1006,
          484,
          231
        ]
      ],
      "bbox": [
        484,
        3,
        1387,
        1003
      ]
    },
    {
      "id": 41,
      "image_id": 21,
      "category_id": 1,
      "area": 1004560.5,
      "iscrowd": 0,
      "segmentation": [
        [
          1212,
          187,
          882,
          -2,
          676,
          0,
          369,
          102,
          53,
          292,
          61,
          505,
          79,
          597,
          546,
          976,
          646,
          897,
          771,
          1079,
          1043,
          1084,
          1405,
          728,
          1215,
          458,
          1261,
          274,
          1220,
          192
        ]
      ],
      "bbox": [
        53,
        -2,
        1352,
        1086
      ]
    },
    {
      "id": 42,
      "image_id": 21,
      "category_id": 2,
      "area": 342163.0,
      "iscrowd": 0,
      "segmentation": [
        [
          569,
          766,
          1156,
          361,
          1402,
          730,
          1038,
          1084,
          758,
          1071,
          566,
          779
        ]
      ],
      "bbox": [
        566,
        361,
        836,
        723
      ]
    },
    {
      "id": 43,
      "image_id": 22,
      "category_id": 2,
      "area": 1076800.0,
      "iscrowd": 0,
      "segmentation": [
        [
          6,
          -2,
          1318,
          -2,
          1454,
          654,
          4,
          890
        ]
      ],
      "bbox": [
        4,
        -2,
        1450,
        892
      ]
    },
    {
      "id": 44,
      "image_id": 23,
      "category_id": 1,
      "area": 1236761.5,
      "iscrowd": 0,
      "segmentation": [
        [
          256,
          6,
          -6,
          293,
          3,
          375,
          215,
          962,
          271,
          956,
          646,
          637,
          953,
          1062,
          1787,
          312,
          1503,
          9,
          250,
          6
        ]
      ],
      "bbox": [
        -6,
        6,
        1793,
        1056
      ]
    },
    {
      "id": 45,
      "image_id": 23,
      "category_id": 2,
      "area": 357083.5,
      "iscrowd": 0,
      "segmentation": [
        [
          240,
          943,
          687,
          528,
          312,
          -3,
          237,
          0,
          -9,
          290,
          218,
          956
        ]
      ],
      "bbox": [
        -9,
        -3,
        696,
        959
      ]
    },
    {
      "id": 46,
      "image_id": 24,
      "category_id": 1,
      "area": 1118327.5,
      "iscrowd": 0,
      "segmentation": [
        [
          530,
          5,
          383,
          61,
          83,
          405,
          330,
          1000,
          375,
          986,
          725,
          697,
          1000,
          1063,
          1197,
          813,
          1747,
          405,
          1350,
          5,
          530,
          -5
        ]
      ],
      "bbox": [
        83,
        -5,
        1664,
        1068
      ]
    },
    {
      "id": 47,
      "image_id": 24,
      "category_id": 2,
      "area": 337550.5,
      "iscrowd": 0,
      "segmentation": [
        [
          388,
          72,
          786,
          641,
          372,
          983,
          325,
          991,
          83,
          400,
          380,
          77
        ]
      ],
      "bbox": [
        83,
        72,
        703,
        919
      ]
    },
    {
      "id": 48,
      "image_id": 25,
      "category_id": 1,
      "area": 933931.0,
      "iscrowd": 0,
      "segmentation": [
        [
          365,
          8,
          274,
          29,
          0,
          310,
          2,
          376,
          161,
          889,
          206,
          897,
          559,
          595,
          785,
          1004,
          961,
          795,
          940,
          665,
          1510,
          419,
          1519,
          351,
          1225,
          8,
          359,
          6
        ]
      ],
      "bbox": [
        0,
        6,
        1519,
        998
      ]
    },
    {
      "id": 49,
      "image_id": 25,
      "category_id": 2,
      "area": 290101.5,
      "iscrowd": 0,
      "segmentation": [
        [
          289,
          25,
          595,
          561,
          563,
          593,
          206,
          900,
          163,
          900,
          0,
          385,
          6,
          308,
          291,
          19
        ]
      ],
      "bbox": [
        0,
        19,
        595,
        881
      ]
    },
    {
      "id": 50,
      "image_id": 26,
      "category_id": 1,
      "area": 751157.5,
      "iscrowd": 0,
      "segmentation": [
        [
          1504,
          671,
          1458,
          371,
          1219,
          89,
          708,
          104,
          626,
          126,
          280,
          317,
          234,
          804,
          265,
          813,
          660,
          613,
          693,
          1050,
          880,
          1041,
          893,
          802,
          1517,
          667
        ]
      ],
      "bbox": [
        234,
        89,
        1283,
        961
      ]
    },
    {
      "id": 51,
      "image_id": 26,
      "category_id": 2,
      "area": 185032.5,
      "iscrowd": 0,
      "segmentation": [
        [
          623,
          143,
          658,
          615,
          267,
          808,
          230,
          800,
          284,
          323,
          623,
          145
        ]
      ],
      "bbox": [
        230,
        143,
        428,
        665
      ]
    },
    {
      "id": 52,
      "image_id": 27,
      "category_id": 1,
      "area": 924824.0,
      "iscrowd": 0,
      "segmentation": [
        [
          1309,
          528,
          1250,
          233,
          1076,
          -2,
          364,
          -2,
          78,
          152,
          4,
          464,
          7,
          623,
          392,
          466,
          435,
          907,
          1269,
          871,
          1309,
          528
        ]
      ],
      "bbox": [
        4,
        -2,
        1305,
        909
      ]
    },
    {
      "id": 53,
      "image_id": 27,
      "category_id": 2,
      "area": 170317.0,
      "iscrowd": 0,
      "segmentation": [
        [
          400,
          438,
          411,
          2,
          364,
          -2,
          80,
          150,
          2,
          485,
          4,
          628,
          397,
          447
        ]
      ],
      "bbox": [
        2,
        -2,
        409,
        630
      ]
    },
    {
      "id": 54,
      "image_id": 28,
      "category_id": 1,
      "area": 777312.0,
      "iscrowd": 0,
      "segmentation": [
        [
          1145,
          2,
          121,
          -2,
          59,
          18,
          8,
          243,
          -2,
          472,
          370,
          297,
          367,
          567,
          400,
          759,
          1270,
          737,
          1267,
          437,
          1154,
          -2
        ]
      ],
      "bbox": [
        -2,
        -2,
        1272,
        761
      ]
    },
    {
      "id": 55,
      "image_id": 29,
      "category_id": 1,
      "area": 621440.5,
      "iscrowd": 0,
      "segmentation": [
        [
          173,
          12,
          121,
          531,
          378,
          482,
          400,
          775,
          990,
          778,
          1053,
          712,
          1021,
          4,
          219,
          0,
          175,
          19
        ]
      ],
      "bbox": [
        121,
        0,
        932,
        778
      ]
    },
    {
      "id": 56,
      "image_id": 29,
      "category_id": 2,
      "area": 124454.5,
      "iscrowd": 0,
      "segmentation": [
        [
          412,
          2,
          380,
          480,
          114,
          531,
          178,
          21,
          219,
          0,
          400,
          -4
        ]
      ],
      "bbox": [
        114,
        -4,
        298,
        535
      ]
    },
    {
      "id": 57,
      "image_id": 30,
      "category_id": 1,
      "area": 1376130.0,
      "iscrowd": 0,
      "segmentation": [
        [
          1166,
          1007,
          1407,
          651,
          1833,
          12,
          5,
          0,
          0,
          889,
          120,
          1079,
          217,
          1082,
          717,
          661,
          1123,
          1041,
          1174,
          1007
        ]
      ],
      "bbox": [
        0,
        0,
        1833,
        1082
      ]
    },
    {
      "id": 58,
      "image_id": 30,
      "category_id": 2,
      "area": 480788.5,
      "iscrowd": 0,
      "segmentation": [
        [
          210,
          1069,
          705,
          392,
          251,
          7,
          2,
          7,
          0,
          882,
          128,
          1071,
          202,
          1061
        ]
      ],
      "bbox": [
        0,
        7,
        705,
        1064
      ]
    },
    {
      "id": 59,
      "image_id": 31,
      "category_id": 1,
      "area": 782227.0,
      "iscrowd": 0,
      "segmentation": [
        [
          285,
          704,
          1195,
          754,
          1223,
          490,
          1261,
          173,
          1214,
          0,
          69,
          -2,
          7,
          104,
          2,
          295,
          26,
          326,
          278,
          209,
          214,
          430,
          276,
          704
        ]
      ],
      "bbox": [
        2,
        -2,
        1259,
        756
      ]
    },
    {
      "id": 60,
      "image_id": 31,
      "category_id": 2,
      "area": 78043.0,
      "iscrowd": 0,
      "segmentation": [
        [
          23,
          319,
          295,
          197,
          352,
          2,
          54,
          0,
          9,
          104,
          4,
          292,
          23,
          321
        ]
      ],
      "bbox": [
        4,
        0,
        348,
        321
      ]
    },
    {
      "id": 61,
      "image_id": 32,
      "category_id": 1,
      "area": 1016000.5,
      "iscrowd": 0,
      "segmentation": [
        [
          21,
          4,
          0,
          71,
          7,
          761,
          59,
          795,
          1111,
          742,
          1171,
          666,
          1192,
          388,
          1673,
          673,
          1700,
          626,
          1342,
          157,
          1076,
          0,
          30,
          0
        ]
      ],
      "bbox": [
        0,
        0,
        1700,
        795
      ]
    },
    {
      "id": 62,
      "image_id": 32,
      "category_id": 2,
      "area": 139317.5,
      "iscrowd": 0,
      "segmentation": [
        [
          1209,
          380,
          1673,
          673,
          1697,
          628,
          1342,
          150,
          1061,
          -9,
          1011,
          -2,
          1211,
          380
        ]
      ],
      "bbox": [
        1011,
        -9,
        686,
        682
      ]
    },
    {
      "id": 63,
      "image_id": 33,
      "category_id": 1,
      "area": 973541.5,
      "iscrowd": 0,
      "segmentation": [
        [
          258,
          956,
          1117,
          1046,
          1212,
          800,
          1253,
          376,
          1189,
          79,
          635,
          15,
          320,
          133,
          2,
          517,
          5,
          600,
          233,
          512,
          146,
          705,
          253,
          956
        ]
      ],
      "bbox": [
        2,
        15,
        1251,
        1031
      ]
    },
    {
      "id": 64,
      "image_id": 33,
      "category_id": 2,
      "area": 97912.0,
      "iscrowd": 0,
      "segmentation": [
        [
          5,
          592,
          264,
          476,
          584,
          35,
          300,
          141,
          0,
          525,
          7,
          597
        ]
      ],
      "bbox": [
        0,
        35,
        584,
        562
      ]
    },
    {
      "id": 65,
      "image_id": 34,
      "category_id": 1,
      "area": 966449.0,
      "iscrowd": 0,
      "segmentation": [
        [
          1016,
          -5,
          356,
          205,
          300,
          302,
          383,
          564,
          724,
          1018,
          1102,
          910,
          1600,
          656,
          1683,
          256,
          1305,
          10,
          989,
          -5
        ]
      ],
      "bbox": [
        300,
        -5,
        1383,
        1023
      ]
    },
    {
      "id": 66,
      "image_id": 35,
      "category_id": 1,
      "area": 967470.0,
      "iscrowd": 0,
      "segmentation": [
        [
          656,
          10,
          189,
          132,
          148,
          218,
          489,
          905,
          532,
          937,
          959,
          864,
          1472,
          589,
          1602,
          194,
          1335,
          8,
          651,
          5
        ]
      ],
      "bbox": [
        148,
        5,
        1454,
        932
      ]
    },
    {
      "id": 67,
      "image_id": 36,
      "category_id": 1,
      "area": 394402.5,
      "iscrowd": 0,
      "segmentation": [
        [
          129,
          863,
          103,
          914,
          119,
          1027,
          170,
          1070,
          1121,
          1076,
          1029,
          949,
          1080,
          789,
          1054,
          730,
          707,
          525,
          499,
          603,
          338,
          703,
          132,
          856
        ]
      ],
      "bbox": [
        103,
        525,
        1018,
        551
      ]
    },
    {
      "id": 68,
      "image_id": 36,
      "category_id": 2,
      "area": 32371.0,
      "iscrowd": 0,
      "segmentation": [
        [
          767,
          1078,
          981,
          894,
          1125,
          1076,
          774,
          1076
        ]
      ],
      "bbox": [
        767,
        894,
        358,
        184
      ]
    },
    {
      "id": 69,
      "image_id": 37,
      "category_id": 1,
      "area": 661113.0,
      "iscrowd": 0,
      "segmentation": [
        [
          332,
          10,
          450,
          657,
          1505,
          510,
          1432,
          347,
          1537,
          347,
          1575,
          82,
          1500,
          0,
          327,
          7
        ]
      ],
      "bbox": [
        327,
        0,
        1248,
        657
      ]
    },
    {
      "id": 70,
      "image_id": 37,
      "category_id": 2,
      "area": 484945.0,
      "iscrowd": 0,
      "segmentation": [
        [
          372,
          142,
          1317,
          62,
          1495,
          497,
          447,
          652,
          375,
          142
        ]
      ],
      "bbox": [
        372,
        62,
        1123,
        590
      ]
    },
    {
      "id": 71,
      "image_id": 38,
      "category_id": 1,
      "area": 697218.5,
      "iscrowd": 0,
      "segmentation": [
        [
          423,
          21,
          507,
          665,
          1547,
          565,
          1578,
          526,
          1526,
          394,
          1597,
          386,
          1673,
          105,
          1618,
          57,
          1615,
          0,
          426,
          10
        ]
      ],
      "bbox": [
        423,
        0,
        1250,
        665
      ]
    },
    {
      "id": 72,
      "image_id": 38,
      "category_id": 2,
      "area": 492784.5,
      "iscrowd": 0,
      "segmentation": [
        [
          460,
          136,
          1400,
          113,
          1563,
          523,
          1550,
          560,
          513,
          660,
          457,
          142
        ]
      ],
      "bbox": [
        457,
        113,
        1106,
        547
      ]
    },
    {
      "id": 73,
      "image_id": 39,
      "category_id": 1,
      "area": 564596.0,
      "iscrowd": 0,
      "segmentation": [
        [
          547,
          5,
          538,
          491,
          1617,
          494,
          1611,
          461,
          1570,
          335,
          1697,
          350,
          1782,
          67,
          1708,
          2
        ]
      ],
      "bbox": [
        538,
        2,
        1244,
        492
      ]
    },
    {
      "id": 74,
      "image_id": 39,
      "category_id": 2,
      "area": 469107.0,
      "iscrowd": 0,
      "segmentation": [
        [
          552,
          8,
          547,
          479,
          1620,
          494,
          1482,
          26
        ]
      ],
      "bbox": [
        547,
        8,
        1073,
        486
      ]
    },
    {
      "id": 75,
      "image_id": 40,
      "category_id": 1,
      "area": 1884250.5,
      "iscrowd": 0,
      "segmentation": [
        [
          222,
          11,
          14,
          174,
          -5,
          1074,
          1757,
          1082,
          1908,
          465,
          1900,
          294,
          1280,
          8,
          222,
          0
        ]
      ],
      "bbox": [
        -5,
        0,
        1913,
        1082
      ]
    },
    {
      "id": 76,
      "image_id": 40,
      "category_id": 2,
      "area": 595259.0,
      "iscrowd": 0,
      "segmentation": [
        [
          928,
          1057,
          1094,
          825,
          -5,
          180,
          -5,
          1060,
          920,
          1065
        ]
      ],
      "bbox": [
        -5,
        180,
        1099,
        885
      ]
    },
    {
      "id": 77,
      "image_id": 41,
      "category_id": 1,
      "area": 1537822.5,
      "iscrowd": 0,
      "segmentation": [
        [
          1630,
          1066,
          1915,
          948,
          1918,
          184,
          1657,
          0,
          281,
          -6,
          42,
          109,
          424,
          948,
          475,
          951,
          930,
          651,
          1354,
          1087,
          1645,
          1072
        ]
      ],
      "bbox": [
        42,
        -6,
        1876,
        1093
      ]
    },
    {
      "id": 78,
      "image_id": 41,
      "category_id": 2,
      "area": 638651.5,
      "iscrowd": 0,
      "segmentation": [
        [
          469,
          942,
          1203,
          442,
          730,
          -3,
          260,
          -6,
          48,
          118,
          421,
          948,
          466,
          948
        ]
      ],
      "bbox": [
        48,
        -6,
        1155,
        954
      ]
    },
    {
      "id": 79,
      "image_id": 42,
      "category_id": 1,
      "area": 565087.5,
      "iscrowd": 0,
      "segmentation": [
        [
          451,
          524,
          1319,
          575,
          1407,
          300,
          1390,
          165,
          1326,
          2,
          185,
          7,
          21,
          219,
          68,
          282,
          434,
          85,
          448,
          214,
          448,
          514
        ]
      ],
      "bbox": [
        21,
        2,
        1386,
        573
      ]
    },
    {
      "id": 80,
      "image_id": 43,
      "category_id": 1,
      "area": 651460.5,
      "iscrowd": 0,
      "segmentation": [
        [
          515,
          -2,
          200,
          227,
          195,
          263,
          520,
          181,
          447,
          290,
          431,
          538,
          1213,
          788,
          1325,
          665,
          1386,
          443,
          1425,
          120,
          1365,
          6,
          1318,
          4
        ]
      ],
      "bbox": [
        195,
        -2,
        1230,
        790
      ]
    },
    {
      "id": 81,
      "image_id": 43,
      "category_id": 2,
      "area": 52048.0,
      "iscrowd": 0,
      "segmentation": [
        [
          700,
          6,
          536,
          161,
          188,
          265,
          188,
          234,
          513,
          -11
        ]
      ],
      "bbox": [
        188,
        -11,
        512,
        276
      ]
    },
    {
      "id": 82,
      "image_id": 44,
      "category_id": 1,
      "area": 708470.5,
      "iscrowd": 0,
      "segmentation": [
        [
          1711,
          102,
          1711,
          67,
          1544,
          8,
          476,
          0,
          361,
          26,
          370,
          76,
          608,
          41,
          611,
          58,
          517,
          144,
          520,
          411,
          1320,
          841,
          1464,
          702,
          1720,
          108
        ]
      ],
      "bbox": [
        361,
        0,
        1359,
        841
      ]
    },
    {
      "id": 83,
      "image_id": 45,
      "category_id": 1,
      "area": 1308677.5,
      "iscrowd": 0,
      "segmentation": [
        [
          -3,
          13,
          53,
          396,
          796,
          1083,
          1200,
          906,
          1530,
          586,
          1760,
          216,
          1780,
          126,
          1756,
          16,
          1700,
          -10,
          -10,
          3
        ]
      ],
      "bbox": [
        -10,
        -10,
        1790,
        1093
      ]
    },
    {
      "id": 84,
      "image_id": 46,
      "category_id": 1,
      "area": 1285255.5,
      "iscrowd": 0,
      "segmentation": [
        [
          459,
          -5,
          421,
          164,
          802,
          994,
          891,
          1032,
          1335,
          1005,
          1883,
          808,
          1916,
          770,
          1913,
          0,
          470,
          -5
        ]
      ],
      "bbox": [
        421,
        -5,
        1495,
        1037
      ]
    },
    {
      "id": 85,
      "image_id": 47,
      "category_id": 1,
      "area": 922060.0,
      "iscrowd": 0,
      "segmentation": [
        [
          12,
          810,
          781,
          787,
          1024,
          710,
          1281,
          440,
          1297,
          344,
          1142,
          6,
          2,
          4,
          10,
          816
        ]
      ],
      "bbox": [
        2,
        4,
        1295,
        812
      ]
    },
    {
      "id": 86,
      "image_id": 48,
      "category_id": 1,
      "area": 1194508.0,
      "iscrowd": 0,
      "segmentation": [
        [
          5,
          -2,
          1332,
          5,
          1524,
          324,
          1505,
          451,
          1283,
          705,
          1018,
          827,
          5,
          929
        ]
      ],
      "bbox": [
        5,
        -2,
        1519,
        931
      ]
    },
    {
      "id": 87,
      "image_id": 48,
      "category_id": 1,
      "area": 0.0,
      "iscrowd": 0,
      "segmentation": [
        [
          1527,
          921,
          1529,
          921,
          1529,
          921,
          1527,
          921
        ]
      ],
      "bbox": [
        1527,
        921,
        2,
        0
      ]
    },
    {
      "id": 88,
      "image_id": 49,
      "category_id": 1,
      "area": 701757.5,
      "iscrowd": 0,
      "segmentation": [
        [
          167,
          648,
          443,
          502,
          1132,
          329,
          1232,
          500,
          1448,
          1075,
          240,
          1070
        ]
      ],
      "bbox": [
        167,
        329,
        1281,
        746
      ]
    },
    {
      "id": 89,
      "image_id": 49,
      "category_id": 2,
      "area": 173390.5,
      "iscrowd": 0,
      "segmentation": [
        [
          451,
          521,
          162,
          643,
          245,
          1072,
          632,
          1083,
          445,
          518
        ]
      ],
      "bbox": [
        162,
        518,
        470,
        565
      ]
    },
    {
      "id": 90,
      "image_id": 50,
      "category_id": 1,
      "area": 959192.0,
      "iscrowd": 0,
      "segmentation": [
        [
          509,
          0,
          65,
          359,
          34,
          468,
          106,
          787,
          871,
          903,
          915,
          853,
          962,
          678,
          1396,
          965,
          1434,
          937,
          1453,
          443,
          1109,
          187,
          1115,
          115,
          1056,
          31,
          506,
          0
        ]
      ],
      "bbox": [
        34,
        0,
        1419,
        965
      ]
    },
    {
      "id": 91,
      "image_id": 50,
      "category_id": 2,
      "area": 236602.0,
      "iscrowd": 0,
      "segmentation": [
        [
          1093,
          196,
          931,
          618,
          1400,
          962,
          1434,
          928,
          1453,
          434,
          1096,
          196
        ]
      ],
      "bbox": [
        931,
        196,
        522,
        766
      ]
    },
    {
      "id": 92,
      "image_id": 51,
      "category_id": 1,
      "area": 951504.5,
      "iscrowd": 0,
      "segmentation": [
        [
          1084,
          52,
          597,
          4,
          525,
          9,
          277,
          170,
          54,
          409,
          22,
          488,
          115,
          777,
          875,
          906,
          909,
          879,
          970,
          684,
          1388,
          959,
          1422,
          938,
          1456,
          429,
          1118,
          193,
          1106,
          104,
          1084,
          45
        ]
      ],
      "bbox": [
        22,
        4,
        1434,
        955
      ]
    },
    {
      "id": 93,
      "image_id": 51,
      "category_id": 2,
      "area": 239152.0,
      "iscrowd": 0,
      "segmentation": [
        [
          1102,
          206,
          931,
          618,
          1400,
          961,
          1429,
          931,
          1456,
          422,
          1125,
          193
        ]
      ],
      "bbox": [
        931,
        193,
        525,
        768
      ]
    },
    {
      "id": 94,
      "image_id": 52,
      "category_id": 1,
      "area": 945665.0,
      "iscrowd": 0,
      "segmentation": [
        [
          1058,
          34,
          593,
          0,
          537,
          0,
          146,
          283,
          53,
          418,
          39,
          479,
          106,
          767,
          874,
          906,
          913,
          874,
          969,
          681,
          1395,
          962,
          1416,
          932,
          1453,
          437,
          1109,
          179,
          1106,
          118,
          1065,
          37
        ]
      ],
      "bbox": [
        39,
        0,
        1414,
        962
      ]
    },
    {
      "id": 95,
      "image_id": 52,
      "category_id": 2,
      "area": 237429.0,
      "iscrowd": 0,
      "segmentation": [
        [
          1086,
          211,
          918,
          630,
          1411,
          960,
          1420,
          930,
          1451,
          446,
          1100,
          186
        ]
      ],
      "bbox": [
        918,
        186,
        533,
        774
      ]
    },
    {
      "id": 96,
      "image_id": 53,
      "category_id": 1,
      "area": 968056.5,
      "iscrowd": 0,
      "segmentation": [
        [
          471,
          -2,
          271,
          115,
          39,
          382,
          15,
          467,
          86,
          741,
          873,
          886,
          978,
          689,
          1393,
          943,
          1415,
          926,
          1454,
          413,
          1119,
          184,
          1097,
          84,
          1041,
          21,
          826,
          -10,
          480,
          -8
        ]
      ],
      "bbox": [
        15,
        -10,
        1439,
        953
      ]
    },
    {
      "id": 97,
      "image_id": 53,
      "category_id": 2,
      "area": 248162.5,
      "iscrowd": 0,
      "segmentation": [
        [
          1080,
          184,
          908,
          604,
          1395,
          932,
          1415,
          902,
          1458,
          408,
          1121,
          171,
          1067,
          176
        ]
      ],
      "bbox": [
        908,
        171,
        550,
        761
      ]
    },
    {
      "id": 98,
      "image_id": 54,
      "category_id": 1,
      "area": 967907.5,
      "iscrowd": 0,
      "segmentation": [
        [
          448,
          -2,
          82,
          307,
          2,
          438,
          87,
          751,
          869,
          864,
          964,
          676,
          1374,
          958,
          1428,
          915,
          1446,
          382,
          1123,
          182,
          1082,
          58,
          1053,
          17,
          920,
          2,
          443,
          0
        ]
      ],
      "bbox": [
        2,
        -2,
        1444,
        960
      ]
    },
    {
      "id": 99,
      "image_id": 54,
      "category_id": 2,
      "area": 249451.5,
      "iscrowd": 0,
      "segmentation": [
        [
          1082,
          164,
          907,
          612,
          1379,
          943,
          1410,
          907,
          1443,
          384,
          1079,
          166
        ]
      ],
      "bbox": [
        907,
        164,
        536,
        779
      ]
    },
    {
      "id": 100,
      "image_id": 55,
      "category_id": 1,
      "area": 948313.5,
      "iscrowd": 0,
      "segmentation": [
        [
          397,
          6,
          69,
          269,
          8,
          395,
          2,
          465,
          76,
          704,
          823,
          860,
          858,
          834,
          919,
          645,
          1358,
          943,
          1369,
          928,
          1450,
          393,
          1106,
          145,
          1102,
          56,
          1086,
          8
        ]
      ],
      "bbox": [
        2,
        6,
        1448,
        937
      ]
    },
    {
      "id": 101,
      "image_id": 55,
      "category_id": 2,
      "area": 256921.5,
      "iscrowd": 0,
      "segmentation": [
        [
          1078,
          145,
          884,
          584,
          1373,
          941,
          1454,
          395,
          1106,
          152
        ]
      ],
      "bbox": [
        884,
        145,
        570,
        796
      ]
    },
    {
      "id": 102,
      "image_id": 56,
      "category_id": 1,
      "area": 1004517.5,
      "iscrowd": 0,
      "segmentation": [
        [
          435,
          -2,
          33,
          323,
          0,
          379,
          5,
          617,
          51,
          741,
          833,
          910,
          897,
          715,
          1312,
          992,
          1364,
          958,
          1435,
          435,
          1115,
          197,
          1092,
          69,
          1061,
          25,
          946,
          -5
        ]
      ],
      "bbox": [
        0,
        -5,
        1435,
        997
      ]
    },
    {
      "id": 103,
      "image_id": 56,
      "category_id": 2,
      "area": 277372.0,
      "iscrowd": 0,
      "segmentation": [
        [
          1079,
          171,
          856,
          630,
          1335,
          1015,
          1364,
          946,
          1441,
          423,
          1076,
          174
        ]
      ],
      "bbox": [
        856,
        171,
        585,
        844
      ]
    },
    {
      "id": 104,
      "image_id": 57,
      "category_id": 1,
      "area": 1001852.5,
      "iscrowd": 0,
      "segmentation": [
        [
          436,
          -6,
          179,
          191,
          10,
          344,
          2,
          608,
          48,
          748,
          779,
          924,
          812,
          895,
          851,
          714,
          1267,
          1020,
          1310,
          995,
          1422,
          446,
          1126,
          228,
          1085,
          130,
          1038,
          44,
          791,
          -6
        ]
      ],
      "bbox": [
        2,
        -6,
        1420,
        1026
      ]
    },
    {
      "id": 105,
      "image_id": 57,
      "category_id": 2,
      "area": 288951.0,
      "iscrowd": 0,
      "segmentation": [
        [
          1057,
          191,
          808,
          653,
          1269,
          1026,
          1318,
          993,
          1420,
          442,
          1067,
          202
        ]
      ],
      "bbox": [
        808,
        191,
        612,
        835
      ]
    },
    {
      "id": 106,
      "image_id": 58,
      "category_id": 1,
      "area": 1055001.5,
      "iscrowd": 0,
      "segmentation": [
        [
          528,
          0,
          158,
          250,
          0,
          397,
          0,
          665,
          28,
          767,
          773,
          982,
          889,
          830,
          1219,
          1069,
          1310,
          1078,
          1450,
          521,
          1158,
          282,
          1136,
          165,
          1095,
          76,
          565,
          0
        ]
      ],
      "bbox": [
        0,
        0,
        1450,
        1078
      ]
    },
    {
      "id": 107,
      "image_id": 58,
      "category_id": 2,
      "area": 304255.0,
      "iscrowd": 0,
      "segmentation": [
        [
          1084,
          258,
          795,
          730,
          1219,
          1063,
          1306,
          1065,
          1450,
          508,
          1097,
          260
        ]
      ],
      "bbox": [
        795,
        258,
        655,
        807
      ]
    },
    {
      "id": 108,
      "image_id": 59,
      "category_id": 1,
      "area": 1069952.0,
      "iscrowd": 0,
      "segmentation": [
        [
          564,
          -2,
          326,
          107,
          2,
          359,
          2,
          540,
          9,
          685,
          61,
          773,
          752,
          997,
          783,
          980,
          830,
          819,
          1154,
          1073,
          1292,
          1066,
          1447,
          530,
          1157,
          290,
          1154,
          159,
          1097,
          88,
          590,
          -9
        ]
      ],
      "bbox": [
        2,
        -9,
        1445,
        1082
      ]
    },
    {
      "id": 109,
      "image_id": 59,
      "category_id": 2,
      "area": 298923.0,
      "iscrowd": 0,
      "segmentation": [
        [
          1107,
          269,
          785,
          745,
          1183,
          1078,
          1283,
          1047,
          1445,
          533,
          1097,
          257
        ]
      ],
      "bbox": [
        785,
        257,
        660,
        821
      ]
    },
    {
      "id": 110,
      "image_id": 60,
      "category_id": 1,
      "area": 1068407.5,
      "iscrowd": 0,
      "segmentation": [
        [
          614,
          38,
          155,
          276,
          4,
          395,
          4,
          576,
          6,
          778,
          674,
          1076,
          789,
          942,
          961,
          1078,
          1263,
          1076,
          1453,
          644,
          1189,
          395,
          1157,
          240,
          1144,
          189,
          621,
          31
        ]
      ],
      "bbox": [
        4,
        31,
        1449,
        1047
      ]
    },
    {
      "id": 111,
      "image_id": 60,
      "category_id": 2,
      "area": 313251.5,
      "iscrowd": 0,
      "segmentation": [
        [
          1129,
          351,
          1446,
          655,
          1261,
          1068,
          965,
          1074,
          714,
          829,
          1134,
          334
        ]
      ],
      "bbox": [
        714,
        334,
        732,
        740
      ]
    },
    {
      "id": 112,
      "image_id": 61,
      "category_id": 1,
      "area": 1062076.5,
      "iscrowd": 0,
      "segmentation": [
        [
          663,
          22,
          411,
          120,
          165,
          277,
          15,
          386,
          2,
          477,
          6,
          736,
          670,
          1063,
          788,
          934,
          929,
          1068,
          1236,
          1077,
          1463,
          677,
          1190,
          384,
          1195,
          240,
          1179,
          190,
          661,
          27
        ]
      ],
      "bbox": [
        2,
        22,
        1461,
        1055
      ]
    },
    {
      "id": 113,
      "image_id": 61,
      "category_id": 2,
      "area": 316991.5,
      "iscrowd": 0,
      "segmentation": [
        [
          1118,
          359,
          709,
          825,
          959,
          1065,
          1227,
          1070,
          1475,
          668,
          1150,
          361
        ]
      ],
      "bbox": [
        709,
        359,
        766,
        711
      ]
    },
    {
      "id": 114,
      "image_id": 62,
      "category_id": 1,
      "area": 1099468.5,
      "iscrowd": 0,
      "segmentation": [
        [
          570,
          0,
          114,
          231,
          14,
          307,
          0,
          458,
          48,
          665,
          653,
          982,
          790,
          870,
          992,
          1065,
          1226,
          1082,
          1495,
          631,
          1248,
          339,
          1243,
          192,
          1224,
          114,
          902,
          7
        ]
      ],
      "bbox": [
        0,
        0,
        1495,
        1082
      ]
    },
    {
      "id": 115,
      "image_id": 62,
      "category_id": 2,
      "area": 347327.0,
      "iscrowd": 0,
      "segmentation": [
        [
          1170,
          300,
          695,
          729,
          1019,
          1070,
          1221,
          1078,
          1492,
          617,
          1168,
          290
        ]
      ],
      "bbox": [
        695,
        290,
        797,
        788
      ]
    },
    {
      "id": 116,
      "image_id": 63,
      "category_id": 1,
      "area": 1104157.5,
      "iscrowd": 0,
      "segmentation": [
        [
          493,
          -2,
          78,
          202,
          0,
          258,
          4,
          519,
          50,
          613,
          628,
          954,
          754,
          854,
          965,
          1076,
          1173,
          1080,
          1489,
          621,
          1250,
          336,
          1254,
          169,
          1230,
          97,
          952,
          -6
        ]
      ],
      "bbox": [
        0,
        -6,
        1489,
        1086
      ]
    },
    {
      "id": 117,
      "image_id": 63,
      "category_id": 2,
      "area": 358271.5,
      "iscrowd": 0,
      "segmentation": [
        [
          1171,
          286,
          663,
          713,
          965,
          1078,
          1165,
          1073,
          1478,
          613,
          1171,
          282
        ]
      ],
      "bbox": [
        663,
        282,
        815,
        796
      ]
    },
    {
      "id": 118,
      "image_id": 64,
      "category_id": 1,
      "area": 1034367.0,
      "iscrowd": 0,
      "segmentation": [
        [
          417,
          7,
          117,
          155,
          67,
          240,
          95,
          495,
          677,
          885,
          802,
          785,
          1032,
          1067,
          1167,
          1075,
          1530,
          597,
          1297,
          292,
          1322,
          145,
          1292,
          47,
          1167,
          5
        ]
      ],
      "bbox": [
        67,
        5,
        1463,
        1070
      ]
    },
    {
      "id": 119,
      "image_id": 64,
      "category_id": 2,
      "area": 359453.0,
      "iscrowd": 0,
      "segmentation": [
        [
          1247,
          250,
          720,
          645,
          1035,
          1070,
          1167,
          1072,
          1530,
          602,
          1250,
          250
        ]
      ],
      "bbox": [
        720,
        250,
        810,
        822
      ]
    },
    {
      "id": 120,
      "image_id": 65,
      "category_id": 1,
      "area": 1017753.0,
      "iscrowd": 0,
      "segmentation": [
        [
          331,
          -7,
          102,
          107,
          68,
          184,
          105,
          465,
          647,
          857,
          768,
          731,
          1013,
          1063,
          1123,
          1068,
          1505,
          602,
          1297,
          284,
          1323,
          121,
          1313,
          60,
          1200,
          0
        ]
      ],
      "bbox": [
        68,
        -7,
        1437,
        1075
      ]
    },
    {
      "id": 121,
      "image_id": 65,
      "category_id": 2,
      "area": 362217.0,
      "iscrowd": 0,
      "segmentation": [
        [
          1223,
          218,
          713,
          623,
          1007,
          1065,
          1105,
          1068,
          1515,
          584,
          1234,
          215
        ]
      ],
      "bbox": [
        713,
        215,
        802,
        853
      ]
    },
    {
      "id": 122,
      "image_id": 66,
      "category_id": 1,
      "area": 1014011.5,
      "iscrowd": 0,
      "segmentation": [
        [
          478,
          5,
          47,
          219,
          5,
          274,
          15,
          460,
          35,
          564,
          539,
          941,
          607,
          841,
          784,
          1072,
          1021,
          1078,
          1370,
          684,
          1192,
          409,
          1223,
          203,
          1196,
          139,
          901,
          -5,
          492,
          7
        ]
      ],
      "bbox": [
        5,
        -5,
        1365,
        1083
      ]
    },
    {
      "id": 123,
      "image_id": 66,
      "category_id": 2,
      "area": 343051.0,
      "iscrowd": 0,
      "segmentation": [
        [
          1109,
          319,
          550,
          739,
          809,
          1076,
          1021,
          1080,
          1368,
          678,
          1105,
          319
        ]
      ],
      "bbox": [
        550,
        319,
        818,
        761
      ]
    },
    {
      "id": 124,
      "image_id": 67,
      "category_id": 1,
      "area": 1007654.5,
      "iscrowd": 0,
      "segmentation": [
        [
          673,
          -13,
          41,
          280,
          45,
          354,
          84,
          595,
          573,
          989,
          645,
          930,
          782,
          1076,
          1056,
          1089,
          1402,
          736,
          1223,
          460,
          1250,
          258,
          1217,
          176,
          869,
          0
        ]
      ],
      "bbox": [
        41,
        -13,
        1361,
        1102
      ]
    },
    {
      "id": 125,
      "image_id": 67,
      "category_id": 2,
      "area": 336434.5,
      "iscrowd": 0,
      "segmentation": [
        [
          573,
          767,
          1141,
          371,
          1400,
          730,
          1045,
          1082,
          767,
          1076,
          573,
          786
        ]
      ],
      "bbox": [
        573,
        371,
        827,
        711
      ]
    },
    {
      "id": 126,
      "image_id": 68,
      "category_id": 1,
      "area": 873734.0,
      "iscrowd": 0,
      "segmentation": [
        [
          912,
          86,
          656,
          148,
          438,
          234,
          206,
          382,
          160,
          428,
          190,
          608,
          182,
          674,
          444,
          924,
          580,
          1036,
          656,
          966,
          722,
          1072,
          1178,
          1076,
          1402,
          876,
          1256,
          608,
          1318,
          418,
          1298,
          352,
          902,
          82
        ]
      ],
      "bbox": [
        160,
        82,
        1242,
        994
      ]
    },
    {
      "id": 127,
      "image_id": 68,
      "category_id": 2,
      "area": 268766.0,
      "iscrowd": 0,
      "segmentation": [
        [
          624,
          876,
          1180,
          512,
          1402,
          902,
          1182,
          1086,
          726,
          1076,
          628,
          892
        ]
      ],
      "bbox": [
        624,
        512,
        778,
        574
      ]
    },
    {
      "id": 128,
      "image_id": 69,
      "category_id": 1,
      "area": 856132.0,
      "iscrowd": 0,
      "segmentation": [
        [
          304,
          -2,
          216,
          183,
          269,
          500,
          369,
          667,
          418,
          1016,
          1137,
          895,
          1113,
          623,
          1218,
          613,
          1300,
          472,
          1306,
          413,
          1139,
          16,
          1018,
          -4
        ]
      ],
      "bbox": [
        216,
        -4,
        1090,
        1020
      ]
    },
    {
      "id": 129,
      "image_id": 69,
      "category_id": 2,
      "area": 311942.5,
      "iscrowd": 0,
      "segmentation": [
        [
          390,
          548,
          1132,
          520,
          1104,
          911,
          418,
          1023,
          379,
          560
        ]
      ],
      "bbox": [
        379,
        520,
        753,
        503
      ]
    },
    {
      "id": 130,
      "image_id": 70,
      "category_id": 1,
      "area": 836950.0,
      "iscrowd": 0,
      "segmentation": [
        [
          295,
          6,
          280,
          140,
          209,
          152,
          245,
          468,
          334,
          459,
          334,
          604,
          377,
          981,
          1102,
          913,
          1088,
          593,
          1195,
          606,
          1302,
          454,
          1302,
          422,
          1143,
          13,
          1081,
          -2,
          306,
          2
        ]
      ],
      "bbox": [
        209,
        -2,
        1093,
        983
      ]
    },
    {
      "id": 131,
      "image_id": 71,
      "category_id": 1,
      "area": 802561.5,
      "iscrowd": 0,
      "segmentation": [
        [
          314,
          10,
          310,
          118,
          222,
          134,
          255,
          440,
          334,
          444,
          326,
          536,
          355,
          930,
          1063,
          926,
          1079,
          610,
          1187,
          614,
          1279,
          514,
          1285,
          461,
          1171,
          55,
          1016,
          2
        ]
      ],
      "bbox": [
        222,
        2,
        1063,
        928
      ]
    },
    {
      "id": 132,
      "image_id": 71,
      "category_id": 2,
      "area": 309910.5,
      "iscrowd": 0,
      "segmentation": [
        [
          346,
          487,
          1073,
          526,
          1059,
          918,
          336,
          946,
          340,
          491
        ]
      ],
      "bbox": [
        336,
        487,
        737,
        459
      ]
    },
    {
      "id": 133,
      "image_id": 72,
      "category_id": 1,
      "area": 798622.5,
      "iscrowd": 0,
      "segmentation": [
        [
          433,
          38,
          376,
          128,
          373,
          202,
          292,
          207,
          283,
          497,
          357,
          485,
          347,
          669,
          307,
          1000,
          1016,
          1045,
          1047,
          766,
          1164,
          773,
          1280,
          669,
          1295,
          616,
          1192,
          192,
          723,
          50,
          438,
          30
        ]
      ],
      "bbox": [
        283,
        30,
        1012,
        1015
      ]
    },
    {
      "id": 134,
      "image_id": 72,
      "category_id": 2,
      "area": 283235.0,
      "iscrowd": 0,
      "segmentation": [
        [
          402,
          557,
          1078,
          676,
          1000,
          1045,
          307,
          990,
          397,
          554
        ]
      ],
      "bbox": [
        307,
        554,
        771,
        491
      ]
    },
    {
      "id": 135,
      "image_id": 73,
      "category_id": 1,
      "area": 778714.5,
      "iscrowd": 0,
      "segmentation": [
        [
          505,
          21,
          445,
          127,
          451,
          191,
          351,
          175,
          316,
          454,
          381,
          470,
          359,
          640,
          302,
          954,
          1010,
          1059,
          1072,
          759,
          1167,
          797,
          1297,
          683,
          1297,
          635,
          1256,
          240,
          1067,
          159,
          767,
          62,
          491,
          21
        ]
      ],
      "bbox": [
        302,
        21,
        995,
        1038
      ]
    },
    {
      "id": 136,
      "image_id": 73,
      "category_id": 2,
      "area": 305638.5,
      "iscrowd": 0,
      "segmentation": [
        [
          397,
          532,
          1110,
          678,
          1002,
          1067,
          283,
          948,
          383,
          535
        ]
      ],
      "bbox": [
        283,
        532,
        827,
        535
      ]
    },
    {
      "id": 137,
      "image_id": 74,
      "category_id": 1,
      "area": 772468.0,
      "iscrowd": 0,
      "segmentation": [
        [
          513,
          39,
          468,
          131,
          470,
          213,
          374,
          201,
          337,
          478,
          415,
          505,
          388,
          654,
          329,
          966,
          1029,
          1080,
          1084,
          778,
          1215,
          811,
          1311,
          705,
          1317,
          654,
          1280,
          264,
          1043,
          158,
          766,
          80,
          531,
          39
        ]
      ],
      "bbox": [
        329,
        39,
        988,
        1041
      ]
    },
    {
      "id": 138,
      "image_id": 74,
      "category_id": 2,
      "area": 290795.0,
      "iscrowd": 0,
      "segmentation": [
        [
          427,
          541,
          1113,
          694,
          1029,
          1076,
          325,
          956,
          421,
          543
        ]
      ],
      "bbox": [
        325,
        541,
        788,
        535
      ]
    }
  ]
}